CHANGES.txt
MANIFEST.in
README.rst
scripts.conf
setup.py
src/zenoss/__init__.py
src/zenoss.toolbox.egg-info/PKG-INFO
src/zenoss.toolbox.egg-info/SOURCES.txt
src/zenoss.toolbox.egg-info/dependency_links.txt
src/zenoss.toolbox.egg-info/entry_points.txt
src/zenoss.toolbox.egg-info/namespace_packages.txt
src/zenoss.toolbox.egg-info/not-zip-safe
src/zenoss.toolbox.egg-info/requires.txt
src/zenoss.toolbox.egg-info/top_level.txt
src/zenoss/toolbox/__init__.py
src/zenoss/toolbox/findposkeyerror.py
src/zenoss/toolbox/zencatalogscan.py
src/zenoss/toolbox/zenindextool.py
src/zenoss/toolbox/zennetworkclean.py
src/zenoss/toolbox/zenrelationscan.py
src/zenoss/toolbox/zodbscan.py
src/zenoss/toolbox/output/zenoss-core-5.0.0_140709.json