Metadata-Version: 1.1
Name: zenoss.toolbox
Version: 0.5.2
Summary: Utilities for analyzing and debugging Zenoss environments.
Home-page: git@github.com:zenoss/zenoss.toolbox.git
Author: Zenoss, Inc.
Author-email: dev@zenoss.com
License: Proprietary
Platform: UNKNOWN
Classifier: Programming Language :: Python
